README.md
setup.py
yamaha_av/YamahaAV.py
yamaha_av/__init__.py
yamaha_av.egg-info/PKG-INFO
yamaha_av.egg-info/SOURCES.txt
yamaha_av.egg-info/dependency_links.txt
yamaha_av.egg-info/top_level.txt