Metadata-Version: 1.1
Name: yamaha-av
Version: 0.10.0
Summary: Control Yamaha Receivers over the network
Home-page: https://pypi.python.org/pypi/yamaha_av
Author: Anthony Casagrande
Author-email: birdapi@gmail.com
License: MIT
Keywords: yamaha av rxv network receivers birdapi
Platform: UNKNOWN
Classifier: Development Status :: 4 - Beta
Classifier: Topic :: Multimedia :: Sound/Audio
Classifier: Topic :: Home Automation
Classifier: Topic :: System :: Networking
Classifier: Programming Language :: Python :: 3
Classifier: Programming Language :: Python :: 3.6
Classifier: Programming Language :: Python :: 3.7
Classifier: Programming Language :: Python :: 3.8
Classifier: License :: OSI Approved :: MIT License
